{
  "parent" : "techtree:agriculture/agriculture",
  "display": {
    "icon": {
      "id": "minecraft:saddle"
    },
    "title": "Animal Taming",
    "description": "Unlocks taming of animals and saddles",
    "announce_to_chat": false,
    "hidden": false
  },
  "criteria": {
    "techtree:agriculture/agriculture": {
      "trigger": "minecraft:impossible"
    }
  },
  "rewards": {
    "recipes": [
      "minecraft:saddle",
      "minecraft:carrot_on_a_stick",
      "minecraft:warped_fungus_on_a_stick",
      "minecraft:lead",
      "minecraft:black_harness",
      "minecraft:blue_harness",
      "minecraft:brown_harness",
      "minecraft:cyan_harness",
      "minecraft:dye_black_harness",
      "minecraft:dye_blue_harness",
      "minecraft:dye_brown_harness",
      "minecraft:dye_cyan_harness",
      "minecraft:dye_gray_harness",
      "minecraft:dye_green_harness",
      "minecraft:dye_light_blue_harness",
      "minecraft:dye_light_gray_harness",
      "minecraft:dye_lime_harness",
      "minecraft:dye_magenta_harness",
      "minecraft:dye_orange_harness",
      "minecraft:dye_pink_harness",
      "minecraft:dye_purple_harness",
      "minecraft:dye_red_harness",
      "minecraft:dye_white_harness",
      "minecraft:dye_yellow_harness",
      "minecraft:gray_harness",
      "minecraft:green_harness",
      "minecraft:light_blue_harness",
      "minecraft:light_gray_harness",
      "minecraft:lime_harness",
      "minecraft:magenta_harness",
      "minecraft:orange_harness",
      "minecraft:pink_harness",
      "minecraft:purple_harness",
      "minecraft:red_harness",
      "minecraft:white_harness",
      "minecraft:yellow_harness",
      "minecraft:wolf_armor"
    ]
  }
}